Metadata-Version: 1.1
Name: libnfldap
Version: 1.0.7
Summary: A client library to generate ipset and iptables rules from LDAP records.
Home-page: https://github.com/mozilla/libnfldap
Author: Julien Vehent
Author-email: jvehent@mozilla.com
License: MPL
Keywords: libnfldap client library
Platform: UNKNOWN
Classifier: Development Status :: 5 - Production/Stable
Classifier: Topic :: Software Development :: Libraries :: Python Modules
Classifier: License :: OSI Approved :: Mozilla Public License 2.0 (MPL 2.0)
